DESCRIPTION.rst
MANIFEST.in
setup.cfg
setup.py
darte7/__init__.py
darte7/darte7.py
darte7.egg-info/PKG-INFO
darte7.egg-info/SOURCES.txt
darte7.egg-info/dependency_links.txt
darte7.egg-info/entry_points.txt
darte7.egg-info/top_level.txt